DESCRIPTION.rst
LICENSE
MANIFEST.in
README.md
setup.py
oide_slurm_assist.egg-info/PKG-INFO
oide_slurm_assist.egg-info/SOURCES.txt
oide_slurm_assist.egg-info/dependency_links.txt
oide_slurm_assist.egg-info/not-zip-safe
oide_slurm_assist.egg-info/requires.txt
oide_slurm_assist.egg-info/top_level.txt
oideslurm/.bowerrc
oideslurm/__init__.py
oideslurm/__init__.pyc
oideslurm/bower.json
oideslurm/config_utils.py
oideslurm/config_utils.pyc
oideslurm/handlers.py
oideslurm/handlers.pyc
oideslurm/settings.py
oideslurm/settings.pyc
oideslurm/urls.py
oideslurm/urls.pyc
oideslurm/mixins/__init__.py
oideslurm/mixins/__init__.pyc
oideslurm/mixins/slurm_mixin.py
oideslurm/mixins/slurm_mixin.pyc
oideslurm/static/slurm.css
oideslurm/static/slurm.html
oideslurm/static/slurm.js
oideslurm/static/slurm_test.js
oideslurm/static/bower_components/angular/.bower.json
oideslurm/static/bower_components/angular/README.md
oideslurm/static/bower_components/angular/angular-csp.css
oideslurm/static/bower_components/angular/angular.js
oideslurm/static/bower_components/angular/angular.min.js
oideslurm/static/bower_components/angular/angular.min.js.gzip
oideslurm/static/bower_components/angular/angular.min.js.map
oideslurm/static/bower_components/angular/bower.json
oideslurm/static/bower_components/angular/index.js
oideslurm/static/bower_components/angular/package.json
oideslurm/static/bower_components/angular-formly/.bower.json
oideslurm/static/bower_components/angular-formly/.eslintignore
oideslurm/static/bower_components/angular-formly/.gitattributes
oideslurm/static/bower_components/angular-formly/CHANGELOG.md
oideslurm/static/bower_components/angular-formly/CODE_OF_CONDUCT.md
oideslurm/static/bower_components/angular-formly/LICENSE
oideslurm/static/bower_components/angular-formly/PATRONS.md
oideslurm/static/bower_components/angular-formly/README.md
oideslurm/static/bower_components/angular-formly/bower.json
oideslurm/static/bower_components/angular-formly/package.json
oideslurm/static/bower_components/angular-formly-templates-bootstrap/.bower.json
oideslurm/static/bower_components/angular-formly-templates-bootstrap/CHANGELOG.md
oideslurm/static/bower_components/angular-formly-templates-bootstrap/CONTRIBUTING.md
