Metadata-Version: 1.1
Name: oide-slurm-assist
Version: 0.7.2
Summary: Online Integrated Development Environment (OIDE) - Slurm Assist App
Home-page: https://github.com/ResearchComputing/oide-slurm-assist
Author: Zebula Sampedro
Author-email: sampedro@colorado.edu
License: AGPLv3, see LICENSE
Platform: UNKNOWN
Classifier: Development Status :: 1 - Planning
Classifier: Intended Audience :: Developers
Classifier: Natural Language :: English
Classifier: Operating System :: Unix
Classifier: Topic :: Software Development :: User Interfaces
Classifier: Topic :: Software Development :: Build Tools
Classifier: Topic :: Text Editors :: Integrated Development Environments (IDE)
Classifier: Topic :: Terminals :: Terminal Emulators/X Terminals
Classifier: License :: OSI Approved :: GNU Affero General Public License v3
Classifier: Programming Language :: Python :: 2.7
Classifier: Programming Language :: JavaScript
